{
  "generatedAt": "2026-03-13T03:10:46.549Z",
  "base": {
    "name": "nextclaw",
    "projectRoot": "/home/runner/work/nextclaw/nextclaw",
    "scope": {
      "includeDirs": [
        "apps",
        "packages",
        "workers",
        "bridge",
        "scripts"
      ],
      "includeExtensions": [
        ".ts",
        ".tsx",
        ".js",
        ".jsx",
        ".mjs",
        ".cjs",
        ".sh",
        ".yml",
        ".yaml"
      ],
      "excludeDirs": [
        ".git",
        ".changeset",
        "node_modules",
        "dist",
        "coverage",
        "build",
        "ui-dist",
        ".turbo"
      ]
    },
    "totals": {
      "files": 477,
      "totalLines": 79568,
      "blankLines": 7985,
      "commentLines": 660,
      "codeLines": 70923
    }
  },
  "benchmark": {
    "name": "openclaw",
    "projectRoot": "/home/runner/work/nextclaw/nextclaw/external/openclaw",
    "scope": {
      "includeDirs": [
        "src",
        "extensions",
        "scripts"
      ],
      "includeExtensions": [
        ".ts",
        ".tsx",
        ".js",
        ".jsx",
        ".mjs",
        ".cjs",
        ".sh",
        ".yml",
        ".yaml"
      ],
      "excludeDirs": [
        ".git",
        ".changeset",
        "node_modules",
        "dist",
        "coverage",
        "build",
        "ui-dist",
        ".turbo"
      ]
    },
    "totals": {
      "files": 5811,
      "totalLines": 1131883,
      "blankLines": 106993,
      "commentLines": 25223,
      "codeLines": 999667
    }
  },
  "comparison": {
    "baseMinusBenchmarkLines": -928744,
    "basePercentOfBenchmark": 7.09,
    "benchmarkMultipleOfBase": 14.1,
    "baseIsLighterByPercent": 92.91
  }
}
